{
  "path" : "tiles/29/S/NB/2015/11/29/0",
  "timestamp" : "2015-11-29T11:21:40.218Z",
  "utmZone" : 29,
  "latitudeBand" : "S",
  "gridSquare" : "NB",
  "datastrip" : {
    "id" : "S2A_OPER_MSI_L1C_DS_MTI__20151129T193058_S20151129T111510_N02.00",
    "path" : "products/2015/11/29/S2A_OPER_PRD_MSIL1C_PDMC_20151201T182509_R137_V20151129T112140_20151129T112140/datastrip/0"
  },
  "tileGeometry" : {
    "type" : "Polygon",
    "crs" : {
      "type" : "name",
      "properties" : {
        "name" : "urn:ogc:def:crs:EPSG:8.8.1:32629"
      }
    },
    "coordinates" : [ [ [ 499980.0, 4200000.0 ], [ 609780.0, 4200000.0 ], [ 609780.0, 4090200.0 ], [ 499980.0, 4090200.0 ], [ 499980.0, 4200000.0 ] ] ]
  },
  "tileDataGeometry" : {
    "type" : "Polygon",
    "crs" : {
      "type" : "name",
      "properties" : {
        "name" : "urn:ogc:def:crs:EPSG:8.8.1:32629"
      }
    },
    "coordinates" : [ [ [ 609779.0, 4173064.328665442 ], [ 609779.0, 4090201.0 ], [ 591833.160291918, 4090201.0 ], [ 594014.173919503, 4100202.684930109 ], [ 597625.495901731, 4116582.58828262 ], [ 604717.977751132, 4149399.361706706 ], [ 609779.0, 4173064.328665442 ] ] ]
  },
  "tileOrigin" : {
    "type" : "Point",
    "crs" : {
      "type" : "name",
      "properties" : {
        "name" : "urn:ogc:def:crs:EPSG:8.8.1:32629"
      }
    },
    "coordinates" : [ 499980.0, 4200000.0 ]
  },
  "dataCoveragePercentage" : 6.13,
  "cloudyPixelPercentage" : 0.0,
  "productName" : "S2A_OPER_PRD_MSIL1C_PDMC_20151201T182509_R137_V20151129T112140_20151129T112140",
  "productPath" : "products/2015/11/29/S2A_OPER_PRD_MSIL1C_PDMC_20151201T182509_R137_V20151129T112140_20151129T112140"
}